eiffel/__init__.py
eiffel/__main__.py
eiffel/callbacks/notifications.py
eiffel/callbacks/plot.py
eiffel/conf/__init__.py
eiffel/conf/callbacks/mattermost.yaml
eiffel/conf/callbacks/plot.yaml
eiffel/conf/datasets/nfv2/full/botiot.yaml
eiffel/conf/datasets/nfv2/full/cicids.yaml
eiffel/conf/datasets/nfv2/full/nb15.yaml
eiffel/conf/datasets/nfv2/full/toniot.yaml
eiffel/conf/datasets/nfv2/sampled/botiot.yaml
eiffel/conf/datasets/nfv2/sampled/cicids.yaml
eiffel/conf/datasets/nfv2/sampled/nb15.yaml
eiffel/conf/datasets/nfv2/sampled/toniot.yaml
eiffel/conf/eiffel.yaml
eiffel/conf/hydra/job_logging/eiffel.yaml
eiffel/conf/model/popoola.yaml
eiffel/conf/partitioner/dumb.yaml
eiffel/conf/partitioner/iid.yaml
eiffel/conf/partitioner/niid_class.yaml
eiffel/conf/poisoning/profile/decrement.yaml
eiffel/conf/poisoning/profile/increment.yaml
eiffel/conf/poisoning/profile/late.yaml
eiffel/conf/poisoning/profile/loud.yaml
eiffel/conf/poisoning/profile/mid.yaml
eiffel/conf/poisoning/profile/redemption.yaml
eiffel/conf/poisoning/profile/stealth.yaml
eiffel/conf/poisoning/type/targeted.yaml
eiffel/conf/poisoning/type/untargeted.yaml
eiffel/conf/strategy/fedavg.yaml
eiffel/conf/strategy/fednoagg.yaml
eiffel/core/__init__.py
eiffel/core/client.py
eiffel/core/errors.py
eiffel/core/experiment.py
eiffel/core/metrics.py
eiffel/core/pool.py
eiffel/core/tests/client_test.py
eiffel/datasets/__init__.py
eiffel/datasets/dataset.py
eiffel/datasets/nfv2.py
eiffel/datasets/partitioners.py
eiffel/datasets/poisoning.py
eiffel/datasets/tests/dataset_test.py
eiffel/datasets/tests/nfv2_test.py
eiffel/datasets/tests/partitioners_test.py
eiffel/datasets/tests/poisoning_test.py
eiffel/models/supervized.py
eiffel/strategy/__init__.py
eiffel/strategy/fednoagg.py
eiffel/utils/__init__.py
eiffel/utils/hydra.py
eiffel/utils/logging.py
eiffel/utils/resolvers.py
eiffel/utils/time.py
eiffel/utils/typing.py
eiffel_framework-0.3.0.dist-info/METADATA
eiffel_framework-0.3.0.dist-info/WHEEL
eiffel_framework-0.3.0.dist-info/entry_points.txt
eiffel_framework-0.3.0.dist-info/RECORD
