Metadata-Version: 2.1
Name: eiffel-framework
Version: 0.3.0
Summary: Evaluation Framework for FL-based intrusion detection using Flower.
License: MIT
Author: phdcybersec
Author-email: 82591009+phdcybersec@users.noreply.github.com
Requires-Python: >=3.10,<3.11
Classifier: License :: OSI Approved :: MIT License
Classifier: Programming Language :: Python :: 3
Classifier: Programming Language :: Python :: 3.10
Requires-Dist: flwr[simulation] (>=1.5.0,<2.0.0)
Requires-Dist: hydra-core (>=1.3.2,<2.0.0)
Requires-Dist: matplotlib (>=3.8.1,<4.0.0)
Requires-Dist: pandas (>=2.0.3,<3.0.0)
Requires-Dist: ray[data]
Requires-Dist: scikit-learn (>=1.3.0,<2.0.0)
Requires-Dist: tensorflow (>=2.10.0,<2.11.0)
Requires-Dist: tqdm (>=4.66.1,<5.0.0)
